dcen/__init__.py
dcen/decoder.py
dcen/encoder.py
dcen-0.1.dist-info/LICENSE
dcen-0.1.dist-info/METADATA
dcen-0.1.dist-info/WHEEL
dcen-0.1.dist-info/top_level.txt
dcen-0.1.dist-info/RECORD
