Metadata-Version: 2.1
Name: dcen
Version: 0.1
Summary: Embed and retrieve hidden data using pixelated color codes in PNG files.
Home-page: https://github.com/cdnserver/DCEN
Author: cdnserver
Author-email: Xest03KmKtZUSETi@hidemail.app
License: MIT
License-File: LICENSE
Requires-Dist: Pillow
